<?xml version="1.0" encoding="utf-8"?>
<Items>
 <Item name="navpda" identifier="navpda" category="Equipment" Tags="smallitem, pda" cargocontaineridentifier="metalcrate" scale="0.5" impactsoundtag="impact_metal_light">  
	<Deconstruct time="15">
      <Item identifier="fpgacircuit" />
      <Item identifier="plastic" />
    </Deconstruct>
    <Fabricate suitablefabricators="fabricator" requiredtime="20" requiresrecipe="true">
      <RequiredSkill identifier="electrical" level="30" />
      <RequiredItem identifier="fpgacircuit" />
      <RequiredItem identifier="plastic" />
    </Fabricate>
    <InventoryIcon texture="Mods/TalentMod - Jobs Extended/TalentGear.png" sourcerect="160,1,40,58" origin="0.5,0.5" />
    <Sprite texture="Mods/TalentMod - Jobs Extended/TalentGear.png" sourcerect="64,32,29,39" depth="0.55" origin="0.5,0.5" />
    <Body width="30" height="40" density="8" />
    <Holdable slots="Any,RightHand,LeftHand" holdangle="30" handle1="-10,0" msg="ItemMsgPickUpSelect" />
    <RemoteController target="navterminal" onlyinownsub="true" msg="ItemMsgInteractSelect" AllowInGameEditing="false" drawhudwhenequipped="true" />
  </Item>
</Items>