<?xml version="1.0" encoding="utf-8"?>

<!--gives 900 xp to friend and 600 to self, so triple the normal xp-->


<Talents>
  <Override>
  <Talent identifier="cannedheat">
    <Icon texture="Content/UI/TalentsIcons2.png" sheetindex="4,3" sheetelementsize="128,128"/>
    <Description tag="talentdescription.crafthighqualitytanks">
      <Replace tag="[qualitybonus]" value="1" color="gui.green"/>
    </Description>
    <Description tag="talentdescription.cannedheat">
      <Replace tag="[allyexperienceamount]" value="15" color="gui.green"/> <!--cosmetic value-->
      <Replace tag="[experienceamount]" value="10" color="gui.green"/> <!--cosmetic value-->
    </Description>              
    <Description tag="talentdescription.maxtriggeruntilmission">
      <Replace tag="[maxtrigger]" value="60" color="gui.green"/> <!--cosmetic value-->
    </Description>
    <AbilityGroupEffect abilityeffecttype="OnAnyMissionCompleted">
      <Abilities>                                            
        <CharacterAbilityGivePermanentStat statidentifier="cannedheat" value="60" removeondeath="false" giveonaddingfirsttime="true" setvalue="true"/> <!--functional value-->
      </Abilities>
    </AbilityGroupEffect>
    <AbilityGroupEffect abilityeffecttype="OnUseRangedWeapon">
      <Conditions>
        <AbilityConditionItem identifiers="accordion"/>
        <AbilityConditionHasPermanentStat statidentifier="cannedheat" min="1" />
      </Conditions>
      <Abilities>
        <CharacterAbilityApplyStatusEffects>
          <StatusEffects>
            <StatusEffect type="OnAbility" target="This">
              <GiveExperience amount="10"/> <!--functional value-->
            </StatusEffect>
          </StatusEffects> 
        </CharacterAbilityApplyStatusEffects>
        <CharacterAbilityApplyStatusEffectsToNearestAlly>
          <StatusEffects>
            <StatusEffect type="OnAbility" target="Character">
              <GiveExperience amount="15"/> <!--functional value-->
            </StatusEffect>
          </StatusEffects>
        </CharacterAbilityApplyStatusEffectsToNearestAlly>
        <CharacterAbilityGivePermanentStat statidentifier="cannedheat" value="-1" removeondeath="false"/>
      </Abilities>
    </AbilityGroupEffect>
    <AbilityGroupEffect abilityeffecttype="None">
      <Abilities>
        <CharacterAbilityGivePermanentStat statidentifier="weldingtoolfuel" stattype="IncreaseFabricationQuality" value="1" />
        <CharacterAbilityGivePermanentStat statidentifier="refillableoxygensource" stattype="IncreaseFabricationQuality" value="1" />
      </Abilities>
    </AbilityGroupEffect>
  </Talent>
  </Override>
</Talents>