<?xml version="1.0" encoding="utf-8"?>
<TalentTrees>
    <!-- CO Multiclass -->
    <TalentTree jobidentifier="commanding_officer">
        <!-- Powerfull in emergancies, more used to comand stuff around.
    Diving suits Special coaliton upgrade, small buff to eveything -->
        <SubTree identifier="captain_primary"
                 nameidentifier="talenttree.primary"
                 type="primary">
            <TalentOptions maxchosentalents="2">
                <TalentOption identifier="bountyhunter" />
                <TalentOption identifier="logisticsexpert" />
                <TalentOption identifier="prodigy" />
                <TalentOption identifier="inspirationalleader" />
                <TalentOption identifier="veteran" />
                <TalentOption identifier="travelingtradesman" />
            </TalentOptions>
            <TalentOptions maxchosentalents="2">
                <TalentOption identifier="emergencymaneuvers" />
                <TalentOption identifier="sailorwithnoname" />
                <TalentOption identifier="camaraderie" />
                <TalentOption identifier="downwiththeship" />
                <TalentOption identifier="gunsmith" />
                <TalentOption identifier="steadytune" />
            </TalentOptions>
        </SubTree>
        <SubTree identifier="gunslinger"
                 type="specialization"
                 requires="captain_primary"
                 blocks="skipper,politician">
            <TalentOptions>
                <TalentOption identifier="quickdraw" />
                <TalentOption identifier="oldhandsomestranger" />
            </TalentOptions>
            <TalentOptions>
                <TalentOption identifier="lonewolf" />
                <TalentOption identifier="deputy" />
                <TalentOption identifier="oldtumble" />
                <TalentOption identifier="oldquickdraw" />
            </TalentOptions>
            <TalentOptions>
                <TalentOption identifier="drunkensailor" />
                <TalentOption identifier="oldsailorwithnoname" />
                <TalentOption identifier="olddrunkensailor" />
            </TalentOptions>
            <TalentOptions>
                <TalentOption identifier="bigguns" />
                <TalentOption identifier="oldbountyhunter" />
            </TalentOptions>
            <TalentOptions>
                <TalentOption identifier="enchance1" />
            </TalentOptions>
        </SubTree>
        <SubTree identifier="skipper"
                 type="specialization"
                 requires="captain_primary"
                 blocks="gunslinger,politician">
            <TalentOptions>
                <TalentOption identifier="leadingbyexample" />
                <TalentOption identifier="oldtravelingtradesman" />
                <TalentOption identifier="oldevasivemaneuvers" />
            </TalentOptions>
            <TalentOptions>
                <TalentOption identifier="helmsman" />
                <TalentOption identifier="oldtrustedcaptain" />
            </TalentOptions>
            <TalentOptions>
                <TalentOption identifier="inspiringpresence" />
                <TalentOption identifier="trickledown" />
                <TalentOption identifier="oldtrucker" />
                <TalentOption identifier="olddownwiththeship" />
                <!-- Changed to when sub floded at least 70% gain a buff -->
            </TalentOptions>
            <TalentOptions>
                <TalentOption identifier="family" />
                <TalentOption identifier="oldesteemedcaptain" />
                <!-- Buffs depended on players inside of game, Expirence -->
            </TalentOptions>
            <TalentOptions>
                <TalentOption identifier="enchance2" />
              </TalentOptions>
        </SubTree>
        <SubTree identifier="politician"
                 type="specialization"
                 requires="captain_primary"
                 blocks="gunslinger,skipper">
            <TalentOptions>
                <TalentOption identifier="commendations" />
            </TalentOptions>
            <TalentOptions>
                <TalentOption identifier="yourreputation" />
                <ShowCaseTalent identifier="affiliation">
                    <TalentOption identifier="affiliation_coalition" />
                    <TalentOption identifier="affiliation_separatists" />
                    <TalentOption identifier="affiliation_huskcult" />
                    <TalentOption identifier="affiliation_clowns" />
                </ShowCaseTalent>
            </TalentOptions>
            <TalentOptions>
                <TalentOption identifier="campaigning" />
                <TalentOption identifier="networking" />
            </TalentOptions>
            <TalentOptions>
                <TalentOption identifier="figurehead" />
            </TalentOptions>
            <TalentOptions>
                <TalentOption identifier="enchance3" />
              </TalentOptions>
        </SubTree>
        <SubTree identifier="shipmaster">
            <TalentOptions>
              <TalentOption identifier="commander" />
              <!-- passibly 1/5 effect, actively when giving an order you get 5/5 and 10 to Every skill. , also 14% damage reduction, when ally gets a skill point 50% chance he gets 10exp -->
            </TalentOptions>
            <TalentOptions>
              <TalentOption identifier="trustbuilding" />
              <TalentOption identifier="positivereinforcment" />
            </TalentOptions>
            <TalentOptions>
              <TalentOption identifier="camaraderie" />
              <TalentOption identifier="redalarm" />
            </TalentOptions>
            <TalentOptions>
              <TalentOption identifier="allhandsondeck" />
              <!--Buffs depended on players inside of game, Defence + Skills -->
            </TalentOptions>
            <TalentOptions>
              <TalentOption identifier="enchance3" />
            </TalentOptions>
          </SubTree>
    </TalentTree>
</TalentTrees>